django_cas_ng/__init__.py
django_cas_ng/backends.py
django_cas_ng/decorators.py
django_cas_ng/middleware.py
django_cas_ng/models.py
django_cas_ng/signals.py
django_cas_ng/utils.py
django_cas_ng/views.py
django_cas_ng/locale/de/LC_MESSAGES/django.po
django_cas_ng/locale/fr/LC_MESSAGES/django.po
django_cas_ng/management/__init__.py
django_cas_ng/management/commands/__init__.py
django_cas_ng/management/commands/django_cas_ng_clean_sessions.py
django_cas_ng/migrations/0001_initial.py
django_cas_ng/migrations/__init__.py
nereo_django_cas_ng-4.0.0.dist-info/DESCRIPTION.rst
nereo_django_cas_ng-4.0.0.dist-info/METADATA
nereo_django_cas_ng-4.0.0.dist-info/RECORD
nereo_django_cas_ng-4.0.0.dist-info/WHEEL
nereo_django_cas_ng-4.0.0.dist-info/metadata.json
nereo_django_cas_ng-4.0.0.dist-info/top_level.txt
