Metadata-Version: 2.0
Name: nereo-django-cas-ng
Version: 4.0.0
Summary: CAS 1.0/2.0 client authentication backend for Django (inherited from django-cas)
Home-page: https://github.com/Nereo/django-cas-ng
Author: Ming Chen
Author-email: mockey.chen@gmail.com
License: BSD
Download-URL: https://github.com/Nereo/django-cas-ng/releases
Keywords: django,cas,cas2,cas3,client,sso,single sign-on,authentication,auth
Platform: UNKNOWN
Classifier: Development Status :: 5 - Production/Stable
Classifier: Environment :: Web Environment
Classifier: Intended Audience :: Developers
Classifier: Framework :: Django
Classifier: License :: OSI Approved :: MIT License
Classifier: Natural Language :: English
Classifier: Operating System :: OS Independent
Classifier: Topic :: Internet :: WWW/HTTP
Classifier: Programming Language :: Python
Classifier: Programming Language :: Python :: 3
Requires-Dist: python-cas (>=1.2.0)
